{"location": {"callable": {}, "screen": {}, "define": {}, "transform": {}, "label": {"day2_angry_ys": ["game/encore_script-sayoriexclusivescenes.rpy", 1309], "warningscreen": ["game/splash.rpy", 344], "autoload": ["game/splash.rpy", 366], "tutorial_route_adv_poemgame_pgexp": ["game/tutorials.rpy", 763], "updateconsole_clearall": ["game/advanced_scripts/console.rpy", 44], "encore_credits": ["game/encore-credits.rpy", 316], "day2_Keith": ["game/Encore-day2.rpy", 486], "day2_nvoid": ["game/Encore-day2.rpy", 2553], "day2_angry_yn": ["game/encore_script-natsukiexclusivescenes.rpy", 1697], "day2_angry_ym": ["game/encore_script-monikaexclusivescenes.rpy", 539], "showpoem": ["game/advanced_scripts/poems.rpy", 920], "yur_first": ["game/encore_script-yuriexclusivescenes.rpy", 1249], "day2_s_n_y2": ["game/Encore-day2.rpy", 2365], "day2_smad2": ["game/Encore-day2.rpy", 1526], "day2_smad3": ["game/Encore-day2.rpy", 1536], "day2_smad1": ["game/Encore-day2.rpy", 1375], "n_hug": ["game/encore_script-natsukiexclusivescenes.rpy", 2357], "day3_npos": ["game/encore_script-natsukiexclusivescenes.rpy", 2381], "day2_yvoid": ["game/Encore-day2.rpy", 2625], "credits2": ["game/advanced_scripts/credits.rpy", 483], "groupAll": ["game/advanced_scripts/autoforward.rpy", 205], "day2_awk_2": ["game/Encore-day2.rpy", 1446], "day2_void": ["game/Encore-day2.rpy", 2138], "updateconsolehistory": ["game/advanced_scripts/console.rpy", 82], "tutorial_route_adv": ["game/tutorials.rpy", 665], "day2_clubroom": ["game/Encore-day2.rpy", 665], "day2_t2": ["game/Encore-day2.rpy", 1253], "ntell_m": ["game/encore_script-yuriexclusivescenes.rpy", 2703], "tutorial_route_adv_poemgame": ["game/tutorials.rpy", 729], "tutorial_route_adv_poemgame_txgrid": ["game/tutorials.rpy", 989], "affectionasignment": ["game/Encore!Script.rpy", 12], "day2_breakfast": ["game/Encore-day2.rpy", 63], "nat_first": ["game/encore_script-natsukiexclusivescenes.rpy", 1097], "n_nohug": ["game/encore_script-natsukiexclusivescenes.rpy", 2489], "day2_hope": ["game/Encore-day2.rpy", 427], "day2_missyou": ["game/encore_script-sayoriexclusivescenes.rpy", 2898], "day1_poemsharing": ["game/Encore-day1.rpy", 711], "day2_ref1": ["game/encore_script-sayoriexclusivescenes.rpy", 2343], "day1_clubend": ["game/Encore-day1.rpy", 2016], "s_share": ["game/encore_script-sayoriexclusivescenes.rpy", 3093], "tell_m": ["game/encore_script-yuriexclusivescenes.rpy", 2637], "day2_tend": ["game/Encore-day2.rpy", 1546], "day2_walktoschool_2": ["game/Encore-day2.rpy", 583], "splashscreen": ["game/splash.rpy", 250], "n_khug": ["game/encore_script-natsukiexclusivescenes.rpy", 2368], "end_tutorial": ["game/tutorials.rpy", 110], "poem_special_4": ["game/advanced_scripts/poems_special.rpy", 54], "poem_special_5": ["game/advanced_scripts/poems_special.rpy", 61], "day3_you": ["game/encore_script-sayoriexclusivescenes.rpy", 3460], "day2_gg": ["game/encore_script-natsukiexclusivescenes.rpy", 1555], "import_ddlc_persistent": ["game/submods/import_ddlc/import_ddlc.rpy", 22], "day3_yconverge": ["game/encore_script-yuriexclusivescenes.rpy", 2730], "day3_nminus": ["game/encore_script-natsukiexclusivescenes.rpy", 2505], "tutorial_route_adv_poemgame_getnum": ["game/tutorials.rpy", 974], "poem_special_10": ["game/advanced_scripts/poems_special.rpy", 98], "poem_special_11": ["game/advanced_scripts/poems_special.rpy", 105], "day2_mvoid": ["game/Encore-day2.rpy", 2767], "tutorial_route_adv_repeat": ["game/tutorials.rpy", 676], "day2_t4": ["game/Encore-day2.rpy", 1275], "day2_t5": ["game/Encore-day2.rpy", 1385], "day2_t6": ["game/Encore-day2.rpy", 1404], "day2_t7": ["game/Encore-day2.rpy", 1418], "zz_mas_poemgame_samplethree": ["game/advanced_scripts/zz_poemgame.rpy", 368], "day2_t1": ["game/Encore-day2.rpy", 1233], "day2_classroom": ["game/Encore-day2.rpy", 619], "day2_t3": ["game/Encore-day2.rpy", 1264], "poem_scene6": ["game/Encore-day1.rpy", 1106], "day2_start": ["game/Encore-day2.rpy", 4], "day2_t8": ["game/Encore-day2.rpy", 1432], "mas_poem_minigame_actone": ["game/advanced_scripts/zz_poemgame.rpy", 438], "button_one_label": ["game/advanced_scripts/zz_hotkey_buttons.rpy", 222], "day3_arrival": ["game/encore_script-natsukiexclusivescenes.rpy", 2147], "mas_poem_minigame_actthree": ["game/advanced_scripts/zz_poemgame.rpy", 516], "poem": ["game/advanced_scripts/script-poemgame.rpy", 177], "day2_walkhome1": ["game/Encore-day2.rpy", 1779], "day2_m_s_n_y": ["game/Encore-day2.rpy", 2327], "day2_caught_y": ["game/encore_script-yuriexclusivescenes.rpy", 1811], "day2_walkhome2": ["game/Encore-day2.rpy", 1817], "button_thr_label": ["game/advanced_scripts/zz_hotkey_buttons.rpy", 230], "day2_n_s_y": ["game/Encore-day2.rpy", 2279], "day2_glitch1_2": ["game/Encore-day2.rpy", 206], "credits": ["game/advanced_scripts/credits.rpy", 392], "day2_breakfast_monika": ["game/Encore-day2.rpy", 102], "updateconsole": ["game/advanced_scripts/console.rpy", 31], "postcredits_loop": ["game/advanced_scripts/credits.rpy", 649], "day2_caught_n": ["game/encore_script-natsukiexclusivescenes.rpy", 1623], "day2_caught_m": ["game/encore_script-monikaexclusivescenes.rpy", 453], "mencore_1": ["game/encore_script-monikaexclusivescenes.rpy", 2], "mencore_3": ["game/encore_script-monikaexclusivescenes.rpy", 579], "mencore_2": ["game/encore_script-monikaexclusivescenes.rpy", 168], "protoype_end": ["game/Encore!Script.rpy", 4], "day2_glitch2": ["game/Encore-day2.rpy", 229], "day2_hugattack": ["game/Encore-day2.rpy", 300], "day2_choice": ["game/Encore-day2.rpy", 1177], "sencore_3": ["game/encore_script-sayoriexclusivescenes.rpy", 2938], "sencore_2": ["game/encore_script-sayoriexclusivescenes.rpy", 541], "sencore_1": ["game/encore_script-sayoriexclusivescenes.rpy", 2], "day2_glitch1_1": ["game/Encore-day2.rpy", 184], "encorestart": ["game/Encore-day1.rpy", 1], "day2_sv1": ["game/Encore-day2.rpy", 2229], "tutorial_route_adv_hkb": ["game/tutorials.rpy", 695], "day2_angry_ny": ["game/encore_script-yuriexclusivescenes.rpy", 1897], "day1_void_monika": ["game/Encore-day1.rpy", 2897], "poem_answer": ["game/Encore-day2.rpy", 1573], "day2_walkhome3": ["game/Encore-day2.rpy", 1936], "day2_angry_ns": ["game/encore_script-sayoriexclusivescenes.rpy", 1291], "day2_smash": ["game/encore_script-sayoriexclusivescenes.rpy", 2176], "day2_nv1": ["game/Encore-day2.rpy", 2238], "day2_svoid": ["game/Encore-day2.rpy", 2470], "poem_special_2": ["game/advanced_scripts/poems_special.rpy", 39], "poem_special_3": ["game/advanced_scripts/poems_special.rpy", 47], "poem_special_1": ["game/advanced_scripts/poems_special.rpy", 30], "poem_special_6": ["game/advanced_scripts/poems_special.rpy", 68], "poem_special_7": ["game/advanced_scripts/poems_special.rpy", 75], "day2_y_s_n2": ["game/Encore-day2.rpy", 2407], "day2_angry_nm": ["game/encore_script-monikaexclusivescenes.rpy", 521], "day2_ref2": ["game/encore_script-sayoriexclusivescenes.rpy", 2376], "poem_special_8": ["game/advanced_scripts/poems_special.rpy", 84], "poem_special_9": ["game/advanced_scripts/poems_special.rpy", 91], "day3_ymain": ["game/encore_script-yuriexclusivescenes.rpy", 2306], "quit": ["game/splash.rpy", 392], "day3_sconverge": ["game/encore_script-sayoriexclusivescenes.rpy", 4367], "day2_sarrive": ["game/encore_script-sayoriexclusivescenes.rpy", 1821], "n_poem1": ["game/Encore-day2.rpy", 1679], "day2_poems": ["game/encore_script-sayoriexclusivescenes.rpy", 1336], "start": ["game/script.rpy", 2], "day2_v2": ["game/encore_script-sayoriexclusivescenes.rpy", 1521], "tutorial_selection_menu": ["game/tutorials.rpy", 92], "day2_v1": ["game/encore_script-sayoriexclusivescenes.rpy", 1361], "drawconsole": ["game/advanced_scripts/console.rpy", 75], "PoseToolPractice": ["game/mod_assets/character_images/pose_tool_practice.rpy", 1], "yencore_1": ["game/encore_script-yuriexclusivescenes.rpy", 2], "sayori_not_sorry_y": ["game/encore_script-yuriexclusivescenes.rpy", 1852], "yencore_3": ["game/encore_script-yuriexclusivescenes.rpy", 1916], "yencore_2": ["game/encore_script-yuriexclusivescenes.rpy", 814], "day1_beginning": ["game/Encore-day1.rpy", 69], "button_two_label": ["game/advanced_scripts/zz_hotkey_buttons.rpy", 226], "sayori_not_sorry_m": ["game/encore_script-monikaexclusivescenes.rpy", 498], "tutorial_route_p8": ["game/tutorials.rpy", 510], "tutorial_route_p9": ["game/tutorials.rpy", 598], "before_main_menu": ["game/splash.rpy", 388], "tutorial_route_p2": ["game/tutorials.rpy", 171], "tutorial_route_p3": ["game/tutorials.rpy", 216], "tutorial_route_p1": ["game/tutorials.rpy", 125], "tutorial_route_p6": ["game/tutorials.rpy", 371], "tutorial_route_p7": ["game/tutorials.rpy", 431], "tutorial_route_p4": ["game/tutorials.rpy", 252], "tutorial_route_p5": ["game/tutorials.rpy", 303], "sayori_sorry_y": ["game/encore_script-yuriexclusivescenes.rpy", 1830], "day2_sinteraction": ["game/encore_script-sayoriexclusivescenes.rpy", 1850], "day2_glitch3": ["game/Encore-day2.rpy", 264], "mas_poem_minigame_acttwo": ["game/advanced_scripts/zz_poemgame.rpy", 482], "sayori_sorry_n": ["game/encore_script-natsukiexclusivescenes.rpy", 1642], "updateconsole_old": ["game/advanced_scripts/console.rpy", 50], "zz_mas_poemgame_sampleone": ["game/advanced_scripts/zz_poemgame.rpy", 355], "sayori_sorry_m": ["game/encore_script-monikaexclusivescenes.rpy", 472], "day2_clubend": ["game/Encore-day2.rpy", 1736], "day2_y_s_n": ["game/Encore-day2.rpy", 2303], "day1_bedroom": ["game/Encore-day1.rpy", 2123], "day2_angry_sm": ["game/encore_script-monikaexclusivescenes.rpy", 558], "updateconsole_loop": ["game/advanced_scripts/console.rpy", 57], "day2_awk": ["game/Encore-day2.rpy", 1287], "day2_angry_sn": ["game/encore_script-natsukiexclusivescenes.rpy", 1719], "zz_mas_poemgame_sampletwo": ["game/advanced_scripts/zz_poemgame.rpy", 361], "tutorial_route_p5_favorite_color": ["game/tutorials.rpy", 355], "day2_yv1": ["game/Encore-day2.rpy", 2247], "tutorial_selection": ["game/tutorials.rpy", 83], "day2_angry_sy": ["game/encore_script-yuriexclusivescenes.rpy", 1874], "day2_walktoschool": ["game/Encore-day2.rpy", 132], "tutorial_route_adv_poemgame_pg_end": ["game/tutorials.rpy", 965], "groupClear": ["game/advanced_scripts/autoforward.rpy", 214], "day2_m_s_n_y2": ["game/Encore-day2.rpy", 2433], "mas_poem_minigame": ["game/advanced_scripts/zz_poemgame.rpy", 846], "poem_scene14": ["game/Encore-day1.rpy", 1764], "y_poem1": ["game/Encore-day2.rpy", 1701], "day2_n_s_y2": ["game/Encore-day2.rpy", 2384], "n_bhug": ["game/encore_script-natsukiexclusivescenes.rpy", 2497], "yur_continued": ["game/encore_script-yuriexclusivescenes.rpy", 832], "day2_sinteraction2": ["game/encore_script-sayoriexclusivescenes.rpy", 2386], "day2_meettheclubs": ["game/Encore-day2.rpy", 1195], "hideconsole": ["game/advanced_scripts/console.rpy", 93], "programmer_meme": ["game/script.rpy", 94], "poem_scene3": ["game/Encore-day1.rpy", 862], "poem_scene2": ["game/Encore-day1.rpy", 787], "poem_scene1": ["game/Encore-day1.rpy", 723], "poem_scene7": ["game/Encore-day1.rpy", 1192], "day1_void": ["game/Encore-day1.rpy", 2568], "poem_scene5": ["game/Encore-day1.rpy", 1028], "poem_scene4": ["game/Encore-day1.rpy", 943], "nat_continued": ["game/encore_script-natsukiexclusivescenes.rpy", 785], "sencore_1b": ["game/encore_script-sayoriexclusivescenes.rpy", 381], "poem_scene9": ["game/Encore-day1.rpy", 1348], "poem_scene8": ["game/Encore-day1.rpy", 1262], "nencore_2": ["game/encore_script-natsukiexclusivescenes.rpy", 765], "nencore_3": ["game/encore_script-natsukiexclusivescenes.rpy", 1738], "nencore_1": ["game/encore_script-natsukiexclusivescenes.rpy", 2], "after_load": ["game/splash.rpy", 349], "day2_confession": ["game/Encore-day2.rpy", 2044], "sayori_not_sorry_n": ["game/encore_script-natsukiexclusivescenes.rpy", 1664], "adjust_mouse_poem": ["game/advanced_scripts/poems.rpy", 962], "poem_scene16": ["game/Encore-day1.rpy", 1928], "poem_scene15": ["game/Encore-day1.rpy", 1847], "example_chapter": ["game/script-example.rpy", 6], "poem_scene13": ["game/Encore-day1.rpy", 1688], "poem_scene12": ["game/Encore-day1.rpy", 1606], "poem_scene11": ["game/Encore-day1.rpy", 1524], "poem_scene10": ["game/Encore-day1.rpy", 1437], "s_noshare": ["game/encore_script-sayoriexclusivescenes.rpy", 3390], "day2_s_n_y": ["game/Encore-day2.rpy", 2258]}}, "size": [1280, 720], "name": "", "version": "", "error": true}